chrono_library_messenger-2.0.2.dist-info/licenses/LICENSE
clm/__init__.py
clm/__main__.py
clm/auth.py
clm/core.py
clm/database.py
chrono_library_messenger-2.0.2.dist-info/METADATA
chrono_library_messenger-2.0.2.dist-info/WHEEL
chrono_library_messenger-2.0.2.dist-info/entry_points.txt
chrono_library_messenger-2.0.2.dist-info/top_level.txt
chrono_library_messenger-2.0.2.dist-info/RECORD
