Metadata-Version: 2.4
Name: chrono-library-messenger
Version: 2.0.2
Summary: Messenger without data transmission
Author-email: "A.A Suvorov" <smartlegiondev@gmail.com>
License-Expression: BSD-3-Clause
Project-URL: Homepage, https://github.com/smartlegionlab/chrono-library-messenger
Classifier: Programming Language :: Python :: 3
Classifier: Programming Language :: Python :: 3.7
Classifier: Programming Language :: Python :: 3.8
Classifier: Programming Language :: Python :: 3.9
Classifier: Programming Language :: Python :: 3.10
Classifier: Programming Language :: Python :: 3.11
Classifier: Programming Language :: Python :: 3.12
Classifier: Operating System :: OS Independent
Classifier: Topic :: Security
Classifier: Topic :: Security :: Cryptography
Classifier: Intended Audience :: End Users/Desktop
Classifier: Environment :: Console
Requires-Python: >=3.8
License-File: LICENSE
Dynamic: license-file
